causalimpactx/__init__.py
causalimpactx/analysis.py
causalimpactx/inferences.py
causalimpactx/misc.py
causalimpactx/model.py
causalimpactx-1.0.0.dist-info/AUTHORS.md
causalimpactx-1.0.0.dist-info/LICENSE.md
causalimpactx-1.0.0.dist-info/METADATA
causalimpactx-1.0.0.dist-info/WHEEL
causalimpactx-1.0.0.dist-info/top_level.txt
causalimpactx-1.0.0.dist-info/RECORD
