Metadata-Version: 2.1
Name: causalimpactx
Version: 1.0.0
Summary: A clone of R version CausalImpact developed by Google
Author-email: Yaseen Esmaeelpour <yaseenes@gmail.com>
Project-URL: Homepage, https://github.com/yaseenesmaeelpour/causalimpactx
Project-URL: Issues, https://github.com/yaseenesmaeelpour/causalimpactx/issues
Classifier: Programming Language :: Python :: 3
Classifier: License :: OSI Approved :: MIT License
Classifier: Operating System :: OS Independent
Requires-Python: >=3.8
License-File: LICENSE.md
License-File: AUTHORS.md
Requires-Dist: pandas
Requires-Dist: numpy
Requires-Dist: scipy
Requires-Dist: pytensor
Requires-Dist: pymc
Requires-Dist: statsmodels
